registeruz_mcp/__init__.py
registeruz_mcp/client.py
registeruz_mcp/prompts.py
registeruz_mcp/resources.py
registeruz_mcp/server.py
registeruz_mcp/models/__init__.py
registeruz_mcp/models/accounting.py
registeruz_mcp/models/classifiers.py
registeruz_mcp/models/enums.py
registeruz_mcp/models/labeled.py
registeruz_mcp/models/responses.py
registeruz_mcp/models/templates.py
registeruz_mcp/tools/__init__.py
registeruz_mcp/tools/classifier_tools.py
registeruz_mcp/tools/count_tools.py
registeruz_mcp/tools/detail_tools.py
registeruz_mcp/tools/download_tools.py
registeruz_mcp/tools/labeled_tools.py
registeruz_mcp/tools/list_tools.py
registeruz_mcp/tools/template_tools.py
registeruz_mcp-0.1.1.dist-info/licenses/LICENSE
registeruz_mcp-0.1.1.dist-info/METADATA
registeruz_mcp-0.1.1.dist-info/WHEEL
registeruz_mcp-0.1.1.dist-info/entry_points.txt
registeruz_mcp-0.1.1.dist-info/top_level.txt
registeruz_mcp-0.1.1.dist-info/RECORD
