Metadata-Version: 2.4
Name: registeruz-mcp
Version: 0.1.1
Summary: MCP server for Slovak Registry of Financial Statements (Register účtovných závierok)
Requires-Python: >=3.12
License-File: LICENSE
Requires-Dist: fastmcp>=2.14.0
Requires-Dist: httpx>=0.28.0
Provides-Extra: dev
Requires-Dist: pytest>=8.0.0; extra == "dev"
Requires-Dist: pytest-asyncio>=0.24.0; extra == "dev"
Requires-Dist: vcrpy>=6.0.0; extra == "dev"
Requires-Dist: pytest-recording>=0.13.0; extra == "dev"
Dynamic: license-file
